scann/__init__.py
scann/data_format/__init__.py
scann/data_format/features_pb2.py
scann/partitioning/__init__.py
scann/partitioning/kmeans_tree_partitioner_pb2.py
scann/partitioning/linear_projection_tree_pb2.py
scann/partitioning/partitioner_pb2.py
scann/proto/__init__.py
scann/proto/auto_tuning_pb2.py
scann/proto/brute_force_pb2.py
scann/proto/centers_pb2.py
scann/proto/crowding_pb2.py
scann/proto/disjoint_restrict_token_pb2.py
scann/proto/distance_measure_pb2.py
scann/proto/exact_reordering_pb2.py
scann/proto/hash_pb2.py
scann/proto/input_output_pb2.py
scann/proto/metadata_pb2.py
scann/proto/min_distance_pb2.py
scann/proto/partitioning_pb2.py
scann/proto/projection_pb2.py
scann/proto/scann_pb2.py
scann/scann_ops/__init__.py
scann/scann_ops/scann_assets_pb2.py
scann/scann_ops/cc/_scann_ops.so
scann/scann_ops/cc/python/scann_pybind.so
scann/scann_ops/py/__init__.py
scann/scann_ops/py/scann_builder.py
scann/scann_ops/py/scann_ops.py
scann/scann_ops/py/scann_ops_pybind.py
scann/scann_ops/py/scann_ops_pybind_backcompat.py
scann/trees/__init__.py
scann/trees/kmeans_tree/__init__.py
scann/trees/kmeans_tree/kmeans_tree_pb2.py
scann-1.4.2.dist-info/METADATA
scann-1.4.2.dist-info/WHEEL
scann-1.4.2.dist-info/top_level.txt
scann-1.4.2.dist-info/RECORD
