Metadata-Version: 2.4
Name: scann
Version: 1.4.2
Summary: Scalable Nearest Neighbor search library
Author-email: "Google Inc." <opensource@google.com>
License-Expression: Apache-2.0
Project-URL: Homepage, https://github.com/google-research/google-research/tree/master/scann
Keywords: machine learning
Classifier: Intended Audience :: Developers
Classifier: Intended Audience :: Education
Classifier: Intended Audience :: Science/Research
Classifier: Programming Language :: Python :: 3
Classifier: Programming Language :: Python :: 3.9
Classifier: Programming Language :: Python :: 3.10
Classifier: Programming Language :: Python :: 3.11
Classifier: Programming Language :: Python :: 3.12
Classifier: Programming Language :: Python :: 3.13
Classifier: Topic :: Scientific/Engineering :: Mathematics
Classifier: Topic :: Software Development :: Libraries :: Python Modules
Classifier: Topic :: Software Development :: Libraries
Requires-Python: <3.14,>=3.9
Requires-Dist: numpy~=2.0
Requires-Dist: protobuf
Provides-Extra: tf
Requires-Dist: tensorflow~=2.20.0; extra == "tf"
